MANIFEST.in
README.md
setup.py
matthew_pack/__init__.py
matthew_pack/matt_funct.py
matthew_pack.egg-info/PKG-INFO
matthew_pack.egg-info/SOURCES.txt
matthew_pack.egg-info/dependency_links.txt
matthew_pack.egg-info/top_level.txt