Metadata-Version: 2.1
Name: matthew-pack
Version: 0.0.1
Summary: Calcalating Matthew Correlation Coefficient for multi class problems
Author: Uri Itai & Natan Katz
